README.md
setup.py
ngcasa/__init__.py
ngcasa.egg-info/PKG-INFO
ngcasa.egg-info/SOURCES.txt
ngcasa.egg-info/dependency_links.txt
ngcasa.egg-info/requires.txt
ngcasa.egg-info/top_level.txt
ngcasa/_ngcasa_utils/__init__.py
ngcasa/_ngcasa_utils/_check_parms.py
ngcasa/_ngcasa_utils/_store.py
ngcasa/calibration/__init__.py
ngcasa/calibration/apply_calibration.py
ngcasa/calibration/solve_calibration.py
ngcasa/deconvolution/__init__.py
ngcasa/deconvolution/deconvolve_adaptive_scale_pixel.py
ngcasa/deconvolution/deconvolve_fast_resolve.py
ngcasa/deconvolution/deconvolve_multiterm_clean.py
ngcasa/deconvolution/deconvolve_point_clean.py
ngcasa/deconvolution/deconvolve_rotation_measure_clean.py
ngcasa/deconvolution/feather.py
ngcasa/deconvolution/is_converged.py
ngcasa/deconvolution/linear_mosaic.py
ngcasa/deconvolution/make_mask.py
ngcasa/deconvolution/restore_model.py
ngcasa/flagging/__init__.py
ngcasa/flagging/auto_clip.py
ngcasa/flagging/auto_rflag.py
ngcasa/flagging/auto_tfcrop.py
ngcasa/flagging/auto_uvbin.py
ngcasa/flagging/elevation.py
ngcasa/flagging/extend.py
ngcasa/flagging/flag_summary.py
ngcasa/flagging/manage_flags.py
ngcasa/flagging/manual_flag.py
ngcasa/flagging/manual_unflag.py
ngcasa/flagging/quack.py
ngcasa/flagging/shadow.py
ngcasa/imaging/__init__.py
ngcasa/imaging/calc_image_cell_size.py
ngcasa/imaging/make_grid.py
ngcasa/imaging/make_gridding_convolution_function.py
ngcasa/imaging/make_image.py
ngcasa/imaging/make_imaging_weight.py
ngcasa/imaging/make_pb.py
ngcasa/imaging/make_psf.py
ngcasa/imaging/make_sd_image.py
ngcasa/imaging/make_sd_psf.py
ngcasa/imaging/make_sd_weight_image.py
ngcasa/imaging/mosaic_rotate_uvw.py
ngcasa/imaging/predict_modelvis_component.py
ngcasa/imaging/predict_modelvis_image.py
ngcasa/imaging/_imaging_utils/__init__.py
ngcasa/imaging/_imaging_utils/_check_imaging_parms.py
ngcasa/imaging/_imaging_utils/_gridding_convolutional_kernels.py
ngcasa/imaging/_imaging_utils/_make_pb_1d.py
ngcasa/imaging/_imaging_utils/_normalize.py
ngcasa/imaging/_imaging_utils/_remove_padding.py
ngcasa/imaging/_imaging_utils/_standard_grid.py
ngcasa/simulator/__init__.py
