Metadata-Version: 2.1
Name: ngcasa
Version: 0.0.11
Summary: Next Generation CASA
Home-page: https://github.com/casangi/ngcasa
Author: National Radio Astronomy Observatory
Author-email: casa-feedback@nrao.edu
License: Apache-2.0
Platform: UNKNOWN
Provides-Extra: dev
